{
  "generated_at": "2026-04-29T13:18:28.938608+00:00",
  "current": {
    "time": "2026-04-29T11:00:00+00:00",
    "Hs_mop_raw": 0.507,
    "Hs_corrected": 0.566,
    "confidence": "MEDIUM",
    "bin": "NW  (290\u2013330\u00b0)",
    "scale_factor": 1.1175,
    "harvest": {
      "time": "2026-04-29T12:30:00+00:00",
      "Hs": 1.7,
      "Dp": 314.3
    },
    "tide": {
      "tide_height_m": 0.67,
      "tide_trend": "rising",
      "next_high_m": 1.2,
      "next_high_t": "2026-04-29 16:17",
      "next_low_m": 0.33,
      "next_low_t": "2026-04-29 21:46"
    },
    "wind": {
      "wind_speed_ms": 1.2,
      "wind_dir_deg": 70,
      "wind_gust_ms": 1.4,
      "wind_class": "offshore"
    }
  }
}